summathaan/__init__.py
summathaan/main.py
summathaan-0.4.dist-info/METADATA
summathaan-0.4.dist-info/WHEEL
summathaan-0.4.dist-info/entry_points.txt
summathaan-0.4.dist-info/top_level.txt
summathaan-0.4.dist-info/RECORD
