Metadata-Version: 2.2
Name: summathaan
Version: 0.4
Requires-Dist: pyttsx3
Dynamic: requires-dist
